akita_fastapi/__init__.py
akita_fastapi/testclient.py
akita_fastapi-0.0.3.dist-info/LICENSE
akita_fastapi-0.0.3.dist-info/METADATA
akita_fastapi-0.0.3.dist-info/WHEEL
akita_fastapi-0.0.3.dist-info/top_level.txt
akita_fastapi-0.0.3.dist-info/RECORD
